odoo/addons/ssi_psychology_consultation_outsource_work/README.rst
odoo/addons/ssi_psychology_consultation_outsource_work/__init__.py
odoo/addons/ssi_psychology_consultation_outsource_work/__manifest__.py
odoo/addons/ssi_psychology_consultation_outsource_work/models/__init__.py
odoo/addons/ssi_psychology_consultation_outsource_work/models/psychology_consultation.py
odoo/addons/ssi_psychology_consultation_outsource_work/models/psychology_consultation_type.py
odoo/addons/ssi_psychology_consultation_outsource_work/static/description/icon.png
odoo/addons/ssi_psychology_consultation_outsource_work/views/psychology_consultation_type_views.xml
odoo/addons/ssi_psychology_consultation_outsource_work/views/psychology_consultation_views.xml
odoo14_addon_ssi_psychology_consultation_outsource_work-14.0.1.2.0.dist-info/METADATA
odoo14_addon_ssi_psychology_consultation_outsource_work-14.0.1.2.0.dist-info/WHEEL
odoo14_addon_ssi_psychology_consultation_outsource_work-14.0.1.2.0.dist-info/top_level.txt
odoo14_addon_ssi_psychology_consultation_outsource_work-14.0.1.2.0.dist-info/RECORD
